{
  "id" : 1133,
  "songNumber" : 155,
  "title" : "क्रुस् हि कॆ पष्",
  "language" : "hindi",
  "capo" : 0,
  "bpm" : 0,
  "timeSignature" : "4/4",
  "hashtags" : [ ],
  "sections" : [ {
    "type" : "verse",
    "label" : "VERSE 1",
    "lines" : [ {
      "text" : "क्रूस ही के पास जहां खून बहा,",
      "chords" : [ {
        "chord" : "G",
        "position" : 0
      } ]
    }, {
      "text" : "दब के गुनाहों से मैं गया",
      "chords" : [ {
        "chord" : "C",
        "position" : 0
      } ]
    }, {
      "text" : "खून से वहां यह दिल साफ हुआ,",
      "chords" : [ {
        "chord" : "G",
        "position" : 0
      } ]
    }, {
      "text" : "उसकी हो तारीफ।",
      "chords" : [ {
        "chord" : "D",
        "position" : 0
      }, {
        "chord" : "G",
        "position" : 12
      } ]
    } ]
  }, {
    "type" : "verse",
    "label" : "VERSE 2",
    "lines" : [ {
      "text" : "उसकी हो तारीफ, उसकी हो तारीफ",
      "chords" : [ {
        "chord" : "G",
        "position" : 0
      } ]
    }, {
      "text" : "खून से वहां यह दिल साफ हुआ, उसकी हो तारीफ।",
      "chords" : [ {
        "chord" : "C",
        "position" : 0
      }, {
        "chord" : "G",
        "position" : 40
      } ]
    } ]
  }, {
    "type" : "verse",
    "label" : "VERSE 3",
    "lines" : [ {
      "text" : "दुर है गुनाह मेरे बिल यकीन",
      "chords" : [ {
        "chord" : "G",
        "position" : 0
      } ]
    }, {
      "text" : "दिल में अब है यीशु तख्त-नशीन",
      "chords" : [ {
        "chord" : "C",
        "position" : 0
      } ]
    }, {
      "text" : "क्रूस ही का गीत मुझको है शीरीन,",
      "chords" : [ {
        "chord" : "G",
        "position" : 0
      } ]
    }, {
      "text" : "उसकी हो तारीफ।"
    } ]
  }, {
    "type" : "verse",
    "label" : "VERSE 4",
    "lines" : [ {
      "text" : "क्रूस का वह चश्मा है बेसबहा",
      "chords" : [ {
        "chord" : "G",
        "position" : 0
      } ]
    }, {
      "text" : "खुश हूं कि मैं उसके पास गया",
      "chords" : [ {
        "chord" : "C",
        "position" : 0
      } ]
    }, {
      "text" : "खूब मुझको यीशु ने साफ किया,",
      "chords" : [ {
        "chord" : "G",
        "position" : 0
      } ]
    }, {
      "text" : "उसकी हो तारीफ",
      "chords" : [ {
        "chord" : "D",
        "position" : 0
      }, {
        "chord" : "G",
        "position" : 12
      } ]
    } ]
  }, {
    "type" : "verse",
    "label" : "VERSE 5",
    "lines" : [ {
      "text" : "आ देख यह चश्मा है साफ सफ्फा",
      "chords" : [ {
        "chord" : "G",
        "position" : 0
      } ]
    }, {
      "text" : "आ ताकि हो तेरे गुनाह माफ",
      "chords" : [ {
        "chord" : "C",
        "position" : 0
      } ]
    }, {
      "text" : "आ इसी वक्त अभी हो तू साफ,",
      "chords" : [ {
        "chord" : "G",
        "position" : 0
      } ]
    }, {
      "text" : "उसकी हो तारीफ।"
    } ]
  } ]
}