{
  "id" : 1209,
  "songNumber" : 231,
  "title" : "YESHU MERA RAJA YESHU MERA PRABHU",
  "language" : "hindi",
  "capo" : 0,
  "bpm" : 0,
  "timeSignature" : "4/4",
  "hashtags" : [ ],
  "sections" : [ {
    "type" : "verse",
    "label" : "VERSE 1",
    "lines" : [ {
      "text" : "यीशु मेरा राजा यीशु मेरा प्रभु",
      "chords" : [ {
        "chord" : "G",
        "position" : 0
      }, {
        "chord" : "C",
        "position" : 15
      } ]
    }, {
      "text" : "वही मेरा सब कुछ है",
      "chords" : [ {
        "chord" : "G",
        "position" : 0
      }, {
        "chord" : "D",
        "position" : 12
      } ]
    }, {
      "text" : "वही उद्धार वही चट्टान",
      "chords" : [ {
        "chord" : "G",
        "position" : 0
      }, {
        "chord" : "C",
        "position" : 11
      } ]
    }, {
      "text" : "यीशु मेरा गढ़ है ।",
      "chords" : [ {
        "chord" : "D",
        "position" : 0
      }, {
        "chord" : "G",
        "position" : 14
      } ]
    } ]
  }, {
    "type" : "verse",
    "label" : "VERSE 2",
    "lines" : [ {
      "text" : "दुनिया में आया मनुष्य बनकर",
      "chords" : [ {
        "chord" : "G",
        "position" : 0
      }, {
        "chord" : "C",
        "position" : 15
      } ]
    }, {
      "text" : "हमें बचाने को (2)",
      "chords" : [ {
        "chord" : "G",
        "position" : 0
      }, {
        "chord" : "D",
        "position" : 11
      } ]
    }, {
      "text" : "लहूभी बहाया प्राण को भी दिया",
      "chords" : [ {
        "chord" : "G",
        "position" : 0
      }, {
        "chord" : "C",
        "position" : 12
      } ]
    }, {
      "text" : "मुक्ति का दाता यीशु है ।",
      "chords" : [ {
        "chord" : "D",
        "position" : 0
      }, {
        "chord" : "G",
        "position" : 20
      } ]
    } ]
  }, {
    "type" : "verse",
    "label" : "VERSE 3",
    "lines" : [ {
      "text" : "भेड़ो की नाई भटक रहा था",
      "chords" : [ {
        "chord" : "G",
        "position" : 0
      }, {
        "chord" : "C",
        "position" : 13
      } ]
    }, {
      "text" : "उसने मुझे आवाज दी (2)",
      "chords" : [ {
        "chord" : "G",
        "position" : 0
      }, {
        "chord" : "D",
        "position" : 11
      } ]
    }, {
      "text" : "पास बुलाया गले से लगाया",
      "chords" : [ {
        "chord" : "G",
        "position" : 0
      }, {
        "chord" : "C",
        "position" : 11
      } ]
    }, {
      "text" : "शांति का दाता यीशु है।",
      "chords" : [ {
        "chord" : "D",
        "position" : 0
      }, {
        "chord" : "G",
        "position" : 19
      } ]
    } ]
  }, {
    "type" : "verse",
    "label" : "VERSE 4",
    "lines" : [ {
      "text" : "उसने कहा माँगो उसने कहा ढूंढो",
      "chords" : [ {
        "chord" : "G",
        "position" : 0
      }, {
        "chord" : "C",
        "position" : 15
      } ]
    }, {
      "text" : "उसने कहा खटखटाओ (2)",
      "chords" : [ {
        "chord" : "G",
        "position" : 0
      }, {
        "chord" : "D",
        "position" : 12
      } ]
    }, {
      "text" : "मैंने उसे मांगा ढूढा खटखटाया",
      "chords" : [ {
        "chord" : "G",
        "position" : 0
      }, {
        "chord" : "C",
        "position" : 16
      } ]
    }, {
      "text" : "यीशु को पा लिया।",
      "chords" : [ {
        "chord" : "D",
        "position" : 0
      }, {
        "chord" : "G",
        "position" : 13
      } ]
    } ]
  } ]
}