{
  "id" : 887,
  "songNumber" : 275,
  "title" : "HE IS JEHOVAH",
  "language" : "english",
  "originalKey" : "G",
  "capo" : 0,
  "bpm" : 0,
  "timeSignature" : "4/4",
  "hashtags" : [ ],
  "sections" : [ {
    "type" : "verse",
    "label" : "VERSE 1",
    "lines" : [ {
      "text" : "He is Jehovah, God of creation,",
      "chords" : [ {
        "chord" : "D",
        "position" : 0
      } ]
    }, {
      "text" : "He is Jehovah, Lord God Almighty,",
      "chords" : [ {
        "chord" : "G",
        "position" : 0
      }, {
        "chord" : "D",
        "position" : 20
      }, {
        "chord" : "A",
        "position" : 26
      } ]
    }, {
      "text" : "The Balm of Gilead, the Rock of Ages,",
      "chords" : [ {
        "chord" : "D",
        "position" : 4
      }, {
        "chord" : "G",
        "position" : 24
      } ]
    }, {
      "text" : "He is Jehovah, the God that healeth thee.",
      "chords" : [ {
        "chord" : "D",
        "position" : 0
      }, {
        "chord" : "A",
        "position" : 19
      }, {
        "chord" : "D",
        "position" : 36
      } ]
    } ]
  }, {
    "type" : "chorus",
    "label" : "CHORUS",
    "lines" : [ {
      "text" : "Sing Hallelujah (4)",
      "chords" : [ {
        "chord" : "D",
        "position" : 10
      } ]
    }, {
      "text" : "He is Jehovah, Lord God Almighty",
      "chords" : [ {
        "chord" : "G",
        "position" : 0
      }, {
        "chord" : "D",
        "position" : 20
      }, {
        "chord" : "A",
        "position" : 26
      } ]
    }, {
      "text" : "He is Jehovah, the God that healeth thee."
    } ]
  }, {
    "type" : "verse",
    "label" : "VERSE 2",
    "lines" : [ {
      "text" : "He is the Great I Am, the God of Abraham,",
      "chords" : [ {
        "chord" : "D",
        "position" : 3
      }, {
        "chord" : "G",
        "position" : 26
      } ]
    }, {
      "text" : "Jehovah Shalom, the God of peace I Am,",
      "chords" : [ {
        "chord" : "D",
        "position" : 2
      }, {
        "chord" : "D",
        "position" : 20
      }, {
        "chord" : "A",
        "position" : 27
      } ]
    }, {
      "text" : "The God of Israel, the Everlasting One,",
      "chords" : [ {
        "chord" : "D",
        "position" : 4
      }, {
        "chord" : "G",
        "position" : 23
      } ]
    }, {
      "text" : "He is Jehovah, the God that healeth thee."
    } ]
  }, {
    "type" : "verse",
    "label" : "VERSE 3",
    "lines" : [ {
      "text" : "He's our Provider, Jehovah Jireh,",
      "chords" : [ {
        "chord" : "D",
        "position" : 5
      }, {
        "chord" : "G",
        "position" : 21
      } ]
    }, {
      "text" : "God of Salvation, God the Messiah,",
      "chords" : [ {
        "chord" : "D",
        "position" : 0
      }, {
        "chord" : "D",
        "position" : 18
      }, {
        "chord" : "A",
        "position" : 29
      } ]
    }, {
      "text" : "The Son is sent to you and testified of Him,",
      "chords" : [ {
        "chord" : "D",
        "position" : 4
      }, {
        "chord" : "G",
        "position" : 27
      } ]
    }, {
      "text" : "He is Jehovah, the God that healeth thee."
    } ]
  } ]
}