{
  "id" : 814,
  "songNumber" : 202,
  "title" : "JESUS BREAKS EVERY FETTER",
  "language" : "english",
  "capo" : 0,
  "bpm" : 0,
  "timeSignature" : "4/4",
  "hashtags" : [ ],
  "sections" : [ {
    "type" : "verse",
    "label" : "VERSE 1",
    "lines" : [ {
      "text" : "I am now on the altar, (3)",
      "chords" : [ {
        "chord" : "D",
        "position" : 5
      }, {
        "chord" : "G",
        "position" : 16
      } ]
    }, {
      "text" : "Which was made for me.",
      "chords" : [ {
        "chord" : "A",
        "position" : 0
      }, {
        "chord" : "D",
        "position" : 19
      } ]
    } ]
  }, {
    "type" : "chorus",
    "label" : "CHORUS",
    "lines" : [ {
      "text" : "Jesus breaks every fetter, (3)",
      "chords" : [ {
        "chord" : "D",
        "position" : 0
      }, {
        "chord" : "G",
        "position" : 19
      } ]
    }, {
      "text" : "For He sets me free!",
      "chords" : [ {
        "chord" : "A",
        "position" : 0
      }, {
        "chord" : "D",
        "position" : 15
      } ]
    }, {
      "text" : "(I will ever, ever praise Him...)"
    }, {
      "text" : "(I will give God the glory...)"
    }, {
      "text" : "(I will shout Hallelujah...)"
    } ]
  }, {
    "type" : "verse",
    "label" : "VERSE 2",
    "lines" : [ {
      "text" : "I will never doubt my Saviour, (3)",
      "chords" : [ {
        "chord" : "D",
        "position" : 7
      }, {
        "chord" : "G",
        "position" : 22
      } ]
    }, {
      "text" : "For He cleanses me.",
      "chords" : [ {
        "chord" : "A",
        "position" : 0
      }, {
        "chord" : "D",
        "position" : 16
      } ]
    } ]
  }, {
    "type" : "verse",
    "label" : "VERSE 3",
    "lines" : [ {
      "text" : "I will rest on His promise, (3)",
      "chords" : [ {
        "chord" : "D",
        "position" : 7
      }, {
        "chord" : "G",
        "position" : 19
      } ]
    }, {
      "text" : "Which is given to me.",
      "chords" : [ {
        "chord" : "A",
        "position" : 0
      }, {
        "chord" : "D",
        "position" : 18
      } ]
    } ]
  }, {
    "type" : "verse",
    "label" : "VERSE 4",
    "lines" : [ {
      "text" : "On the other side of Jordan,",
      "chords" : [ {
        "chord" : "D",
        "position" : 7
      }, {
        "chord" : "G",
        "position" : 21
      } ]
    }, {
      "text" : "In the sweet fields of Eden",
      "chords" : [ {
        "chord" : "D",
        "position" : 7
      }, {
        "chord" : "A",
        "position" : 23
      } ]
    }, {
      "text" : "Where the Tree of Life is blooming,",
      "chords" : [ {
        "chord" : "D",
        "position" : 10
      }, {
        "chord" : "G",
        "position" : 26
      } ]
    }, {
      "text" : "There is rest for me.",
      "chords" : [ {
        "chord" : "A",
        "position" : 0
      }, {
        "chord" : "D",
        "position" : 18
      } ]
    } ]
  } ]
}